image_processing_cesarhvb/__init__.py
image_processing_cesarhvb/processing/__init__.py
image_processing_cesarhvb/processing/combination.py
image_processing_cesarhvb/processing/transformation.py
image_processing_cesarhvb/utils/__init__.py
image_processing_cesarhvb/utils/io.py
image_processing_cesarhvb/utils/plot.py
image_processing_cesarhvb-0.0.1.dist-info/METADATA
image_processing_cesarhvb-0.0.1.dist-info/WHEEL
image_processing_cesarhvb-0.0.1.dist-info/top_level.txt
image_processing_cesarhvb-0.0.1.dist-info/RECORD
