Metadata-Version: 2.1
Name: image-processing-cesarhvb
Version: 0.0.1
Summary: Image processing package
Home-page: https://github.com/cesarhenrq/Python/tree/main/image-processing-cesarhvb-package
Author: César Henrique
Author-email: cesaarhvb@gmail.com
License: UNKNOWN
Platform: UNKNOWN
Requires-Python: >=3.8
Requires-Dist: matplotlib
Requires-Dist: numpy
Requires-Dist: scikit-image (>=0.16.1)
